nonaybay/__init__.py
nonaybay/__main__.py
nonaybay/configuration/__init__.py
nonaybay/configuration/variables.py
nonaybay/create_directory/__init__.py
nonaybay/create_directory/index.py
nnbnonaybay-0.0.1.53330.dist-info/LICENSE
nnbnonaybay-0.0.1.53330.dist-info/METADATA
nnbnonaybay-0.0.1.53330.dist-info/WHEEL
nnbnonaybay-0.0.1.53330.dist-info/top_level.txt
nnbnonaybay-0.0.1.53330.dist-info/RECORD
