Metadata-Version: 2.1
Name: nnbnonaybay
Version: 0.0.1.53330
Summary: Basicão
Home-page: UNKNOWN
Author: nonaybay
Author-email: rafaelvenancio@protonmail.com
License: UNKNOWN
Platform: UNKNOWN
Classifier: Programming Language :: Python :: 3
Requires-Python: >=3
Requires-Dist: pick
